{
    "id": 931550,
    "name": "frostbite circles",
    "author": "coolemmaboy",
    "creators": [],
    "verifier": "fayodayo",
    "verification": "https://www.youtube.com/watch?v=Qs32Bw6hsrQ",
    "percentToQualify": "70",
    "password": "Sapphire",
    "records": [
                                      {
            "user": "ryanbro_hi",
            "link": "https://youtu.be/EvQ2PchCImo",
            "percent": 100
        },
                                                                      {
            "user": "DDev_",
            "link": "https://youtu.be/neoqNp2WQQk?si=JG-m3In-XsXiIYXU",
            "percent": 100
        },
                            {
            "user": "ScarlettParacosm",
            "link": "https://youtu.be/R9qkohsAKg0?si=nqvUcmf2AiaObnO0",
            "percent": 100
        },
                                                      {
            "user": "azatisbanana",
            "link": "https://youtu.be/FWABX-XrdcQ?si=KS5nn7sutSxJeFxT",
            "percent": 100
        }
    ]
}
